{"is_source_file": true, "format": "Python", "description": "This file implements authentication endpoints for user registration and login using FastAPI, SQLAlchemy, and custom security functions. It defines API routes for registering new users and obtaining JWT tokens, including database interactions and response models.", "external_files": ["src.core.config", "src.core.db", "src.core.security", "src.models.models", "src.schemas.schemas"], "external_methods": ["get_settings", "get_db", "create_access_token", "get_password_hash", "verify_password"], "published": ["router"], "classes": [], "methods": [{"name": "register_user(payload: UserCreate, db: AsyncSession = Depends(get_db))", "description": "Handles user registration, checking for existing email, creating a new user, and saving it to the database.", "scope": "", "scopeKind": ""}, {"name": "login(payload: UserLogin, db: AsyncSession = Depends(get_db))", "description": "Authenticates user credentials and issues a JWT token upon successful login.", "scope": "", "scopeKind": ""}], "calls": ["select", "get_password_hash", "verify_password", "create_access_token", "db.execute", "db.add", "db.flush", "db.commit", "db.refresh"], "search-terms": ["FastAPI auth", "JWT token login", "user registration endpoint", "SQLAlchemy async", "auth router"], "state": 2, "file_id": 13, "knowledge_revision": 28, "git_revision": "", "ctags": [{"_type": "tag", "name": "login", "path": "/home/kavia/workspace/code-generation/real-estate-image-enhancer-73996-74007/backend/src/routers/auth.py", "pattern": "/^async def login(payload: UserLogin, db: AsyncSession = Depends(get_db)):$/", "language": "Python", "kind": "function", "signature": "(payload: UserLogin, db: AsyncSession = Depends(get_db))"}, {"_type": "tag", "name": "register_user", "path": "/home/kavia/workspace/code-generation/real-estate-image-enhancer-73996-74007/backend/src/routers/auth.py", "pattern": "/^async def register_user(payload: UserCreate, db: AsyncSession = Depends(get_db)):$/", "language": "Python", "kind": "function", "signature": "(payload: UserCreate, db: AsyncSession = Depends(get_db))"}, {"_type": "tag", "name": "router", "path": "/home/kavia/workspace/code-generation/real-estate-image-enhancer-73996-74007/backend/src/routers/auth.py", "pattern": "/^router = APIRouter()$/", "language": "Python", "kind": "variable"}, {"_type": "tag", "name": "settings", "path": "/home/kavia/workspace/code-generation/real-estate-image-enhancer-73996-74007/backend/src/routers/auth.py", "pattern": "/^settings = get_settings()$/", "language": "Python", "kind": "variable"}], "hash": "c1e3e2283591f34f4621c5d3bd24b566", "format-version": 4, "code-base-name": "backend", "filename": "backend/src/routers/auth.py", "fields": [{"name": "router = APIRouter()", "scope": "", "scopeKind": "", "description": "unavailable"}, {"name": "settings = get_settings()", "scope": "", "scopeKind": "", "description": "unavailable"}], "revision_history": [{"28": ""}]}